vekterdb/__init__.py
vekterdb/vekterdb.py
vekterdb-0.2.2.dist-info/LICENSE
vekterdb-0.2.2.dist-info/METADATA
vekterdb-0.2.2.dist-info/WHEEL
vekterdb-0.2.2.dist-info/top_level.txt
vekterdb-0.2.2.dist-info/RECORD
